rowing/__init__.py
rowing/_compat.py
rowing/utils.py
rowing-0.3.1.dist-info/LICENSE
rowing-0.3.1.dist-info/METADATA
rowing-0.3.1.dist-info/WHEEL
rowing-0.3.1.dist-info/entry_points.txt
rowing-0.3.1.dist-info/top_level.txt
rowing-0.3.1.dist-info/RECORD
