Metadata-Version: 2.1
Name: rowing
Version: 0.3.1
Summary: Library for loading and presenting data from the worldrowing.com
Home-page: https://github.com/matthewghgriffiths/rowing
Author: Matthew Griffiths
Author-email: matthewghgriffiths@gmail.com
License: MIT
Requires-Python: >=3.8
License-File: LICENSE
Requires-Dist: numpy (>=1.21.0)
Requires-Dist: scipy (>=1.7.0)
Requires-Dist: pandas (>=1.3.0)
Requires-Dist: matplotlib (>=3.5.1)
Requires-Dist: tqdm (>=4.0.0)
Provides-Extra: garmin
Requires-Dist: garminconnect (>=0.1.45) ; extra == 'garmin'
Requires-Dist: fitparse (>=1.2.0) ; extra == 'garmin'
Requires-Dist: openpyxl (>=3.0.0) ; extra == 'garmin'
Requires-Dist: pyarrow (>=7.0.0) ; extra == 'garmin'
Provides-Extra: gpx
Requires-Dist: gpxpy (>=1.5.0) ; extra == 'gpx'
Requires-Dist: fitparse (>=1.2.0) ; extra == 'gpx'
Provides-Extra: req
Requires-Dist: requests (>=2.27.1) ; extra == 'req'
Provides-Extra: worldrowing
Requires-Dist: streamlit (>=1.22.0) ; extra == 'worldrowing'
Requires-Dist: plotly (>=5.14.1) ; extra == 'worldrowing'
